cache_dit/__init__.py
cache_dit/_version.py
cache_dit/envs.py
cache_dit/logger.py
cache_dit/profiler.py
cache_dit/summary.py
cache_dit/utils.py
cache_dit/caching/.gitignore
cache_dit/caching/__init__.py
cache_dit/caching/cache_interface.py
cache_dit/caching/cache_types.py
cache_dit/caching/forward_pattern.py
cache_dit/caching/params_modifier.py
cache_dit/caching/utils.py
cache_dit/caching/block_adapters/__init__.py
cache_dit/caching/block_adapters/adapters.py
cache_dit/caching/block_adapters/block_adapters.py
cache_dit/caching/block_adapters/block_registers.py
cache_dit/caching/cache_adapters/__init__.py
cache_dit/caching/cache_adapters/cache_adapter.py
cache_dit/caching/cache_blocks/__init__.py
cache_dit/caching/cache_blocks/offload_utils.py
cache_dit/caching/cache_blocks/pattern_0_1_2.py
cache_dit/caching/cache_blocks/pattern_3_4_5.py
cache_dit/caching/cache_blocks/pattern_base.py
cache_dit/caching/cache_blocks/pattern_utils.py
cache_dit/caching/cache_contexts/__init__.py
cache_dit/caching/cache_contexts/cache_config.py
cache_dit/caching/cache_contexts/cache_context.py
cache_dit/caching/cache_contexts/cache_manager.py
cache_dit/caching/cache_contexts/context_manager.py
cache_dit/caching/cache_contexts/prune_config.py
cache_dit/caching/cache_contexts/prune_context.py
cache_dit/caching/cache_contexts/prune_manager.py
cache_dit/caching/cache_contexts/calibrators/__init__.py
cache_dit/caching/cache_contexts/calibrators/base.py
cache_dit/caching/cache_contexts/calibrators/foca.py
cache_dit/caching/cache_contexts/calibrators/taylorseer.py
cache_dit/caching/patch_functors/__init__.py
cache_dit/caching/patch_functors/functor_base.py
cache_dit/caching/patch_functors/functor_chroma.py
cache_dit/caching/patch_functors/functor_dit.py
cache_dit/caching/patch_functors/functor_flux.py
cache_dit/caching/patch_functors/functor_hidream.py
cache_dit/caching/patch_functors/functor_hunyuan_dit.py
cache_dit/caching/patch_functors/functor_ltx2.py
cache_dit-1.2.0.dist-info/licenses/LICENSE
cache_dit-1.2.0.dist-info/METADATA
cache_dit-1.2.0.dist-info/WHEEL
cache_dit-1.2.0.dist-info/entry_points.txt
cache_dit-1.2.0.dist-info/top_level.txt
cache_dit-1.2.0.dist-info/RECORD
