Metadata-Version: 2.4
Name: cache_dit
Version: 1.2.0
Summary: A PyTorch-native and Flexible Inference Engine with Hybrid Cache Acceleration and Parallelism for 🤗DiTs.
Author: DefTruth, vipshop.com, etc.
Maintainer: DefTruth, vipshop.com, etc
Project-URL: Repository, https://github.com/vipshop/cache-dit
Project-URL: Homepage, https://github.com/vipshop/cache-dit
Project-URL: GitHub, https://github.com/vipshop/cache-dit
Requires-Python: >=3.10
License-File: LICENSE
Requires-Dist: pyyaml
Requires-Dist: torch>=2.7.1
Requires-Dist: diffusers>=0.36.0
Requires-Dist: transformers>=4.55.2
Provides-Extra: parallelism
Requires-Dist: einops>=0.8.1; extra == "parallelism"
Provides-Extra: quantization
Requires-Dist: torchao>=0.14.1; extra == "quantization"
Requires-Dist: bitsandbytes>=0.48.1; extra == "quantization"
Provides-Extra: metrics
Requires-Dist: scipy; extra == "metrics"
Requires-Dist: scikit-image; extra == "metrics"
Requires-Dist: image-reward; extra == "metrics"
Requires-Dist: lpips==0.1.4; extra == "metrics"
Provides-Extra: serving
Requires-Dist: fastapi>=0.104.0; extra == "serving"
Requires-Dist: uvicorn>=0.24.0; extra == "serving"
Requires-Dist: pydantic>=2.0.0; extra == "serving"
Provides-Extra: dev
Requires-Dist: packaging; extra == "dev"
Requires-Dist: pre-commit; extra == "dev"
Requires-Dist: pytest<8.0.0,>=7.0.0; extra == "dev"
Requires-Dist: pytest-html; extra == "dev"
Requires-Dist: expecttest; extra == "dev"
Requires-Dist: hypothesis; extra == "dev"
Requires-Dist: accelerate; extra == "dev"
Requires-Dist: peft; extra == "dev"
Requires-Dist: protobuf; extra == "dev"
Requires-Dist: sentencepiece; extra == "dev"
Requires-Dist: opencv-python-headless; extra == "dev"
Requires-Dist: ftfy; extra == "dev"
Requires-Dist: scikit-image; extra == "dev"
Provides-Extra: docs
Requires-Dist: mkdocs>=1.5.0; extra == "docs"
Requires-Dist: mkdocs-api-autonav; extra == "docs"
Requires-Dist: mkdocs-material; extra == "docs"
Requires-Dist: mkdocstrings-python; extra == "docs"
Requires-Dist: mkdocs-gen-files; extra == "docs"
Requires-Dist: mkdocs-awesome-nav; extra == "docs"
Requires-Dist: mkdocs-glightbox; extra == "docs"
Requires-Dist: mkdocs-git-revision-date-localized-plugin; extra == "docs"
Requires-Dist: mkdocs-minify-plugin; extra == "docs"
Requires-Dist: regex; extra == "docs"
Requires-Dist: ruff; extra == "docs"
Requires-Dist: pydantic; extra == "docs"
Provides-Extra: all
Requires-Dist: cache-dit[parallelism]; extra == "all"
Requires-Dist: cache-dit[quantization]; extra == "all"
Requires-Dist: cache-dit[metrics]; extra == "all"
Requires-Dist: cache-dit[serving]; extra == "all"
Dynamic: license-file
Dynamic: requires-python
